src/__init__.py
src/db_wrapper.py
src/mysql.py
hamon_ai_database-0.0.1.dist-info/METADATA
hamon_ai_database-0.0.1.dist-info/WHEEL
hamon_ai_database-0.0.1.dist-info/top_level.txt
hamon_ai_database-0.0.1.dist-info/RECORD
